processing/__init__.py
processing/combination.py
processing/transformation.py
utils/__init__.py
utils/io.py
utils/plot.py
processamento_imagem_nil-0.0.1.dist-info/METADATA
processamento_imagem_nil-0.0.1.dist-info/WHEEL
processamento_imagem_nil-0.0.1.dist-info/top_level.txt
processamento_imagem_nil-0.0.1.dist-info/RECORD
