Metadata-Version: 2.1
Name: processamento-imagem-nil
Version: 0.0.1
Summary: Processamento de Imagens
Home-page: https://github.com/VicenteAguiar/Bootcamp_Data_Science_Unimed
Author: Elenilton Vicente de Aguiar
Author-email: aguiar14564@gmail.com
Requires-Python: >=3.8
